LICENSE
MANIFEST.in
requirements.txt
setup.py
mm/__init__.py
mm/__main__.py
mm/basecommand.py
mm/config.py
mm/connection.py
mm/crawlJson.py
mm/enum.py
mm/exceptions.py
mm/github.py
mm/health_check.py
mm/jinja2htmlcompress.py
mm/local_store.py
mm/parsehelp.py
mm/project.py
mm/request.py
mm/runner.py
mm/sfdc_client.py
mm/util.py
mm/vf.py
mm/xmltodict.py
mm.egg-info/PKG-INFO
mm.egg-info/SOURCES.txt
mm.egg-info/dependency_links.txt
mm.egg-info/entry_points.txt
mm.egg-info/requires.txt
mm.egg-info/top_level.txt
mm/bin/MavensMateWindowServer.app/Contents/Info.plist
mm/bin/MavensMateWindowServer.app/Contents/PkgInfo
mm/bin/MavensMateWindowServer.app/Contents/MacOS/MavensMateWindowServer
mm/bin/MavensMateWindowServer.app/Contents/Resources/MavensMateWindowServer.icns
mm/bin/MavensMateWindowServer.app/Contents/Resources/mm-2.icns
mm/bin/MavensMateWindowServer.app/Contents/Resources/en.lproj/Credits.rtf
mm/bin/MavensMateWindowServer.app/Contents/Resources/en.lproj/InfoPlist.strings
mm/bin/MavensMateWindowServer.app/Contents/Resources/en.lproj/MainMenu.nib
mm/commands/__init__.py
mm/commands/code_assist.py
mm/commands/debug.py
mm/commands/deploy.py
mm/commands/metadata.py
mm/commands/misc.py
mm/commands/project.py
mm/commands/server.py
mm/commands/unittest.py
mm/config/atom.json
mm/config/brackets.json
mm/config/st3.json
mm/server/__init__.py
mm/server/mmserver.py
mm/server/lib/__init__.py
mm/server/lib/config.py
mm/server/lib/endpoints.py
mm/server/lib/handler.py
mm/server/lib/server.py
mm/server/lib/server_threaded.py
mm/server/lib/util.py
mm/sforce/__init__.py
mm/sforce/apex.py
mm/sforce/base.py
mm/sforce/metadata.py
mm/sforce/partner.py
mm/sforce/tooling.py
mm/sforce/metadata/apex.json
mm/sforce/metadata/default_child_metadata.json
mm/sforce/metadata/default_metadata.json
mm/ui/__init__.py
mm/ui/resources/bootstrap/css/bootstrap-docs.css
mm/ui/resources/bootstrap/css/bootstrap-responsive.css
mm/ui/resources/bootstrap/css/bootstrap.css
mm/ui/resources/bootstrap/css/prettify.css
mm/ui/resources/bootstrap/img/glyphicons-halflings-white.png
mm/ui/resources/bootstrap/img/glyphicons-halflings.png
