Metadata-Version: 1.0
Name: mm
Version: 0.2.5
Summary: CLI for MavensMate
Home-page: https://github.com/joeferraro/mm
Author: @joeferraro
Author-email: info@mavensmate.com
License: GNU v2
Keywords: mavensmate salesforce salesorce1 force.com ide cli
Platform: UNKNOWN
